dataframes_haystack/__about__.py
dataframes_haystack/__init__.py
dataframes_haystack/components/__init__.py
dataframes_haystack/components/converters/__init__.py
dataframes_haystack/components/converters/_common.py
dataframes_haystack/components/converters/_utils.py
dataframes_haystack/components/converters/pandas.py
dataframes_haystack/components/converters/polars.py
dataframes_haystack-0.0.5.dist-info/METADATA
dataframes_haystack-0.0.5.dist-info/WHEEL
dataframes_haystack-0.0.5.dist-info/licenses/LICENSE
dataframes_haystack-0.0.5.dist-info/RECORD
