Metadata-Version: 2.4
Name: dataframes-haystack
Version: 0.0.5
Summary: Haystack custom components for your favourite dataframe library.
Project-URL: Documentation, https://github.com/EdAbati/dataframes-haystack#readme
Project-URL: Issues, https://github.com/EdAbati/dataframes-haystack/issues
Project-URL: Source, https://github.com/EdAbati/dataframes-haystack
Author: Edoardo Abati
License: MIT License
License-File: LICENSE
Keywords: ai,dataframe,haystack,llm,machine-learning,nlp,pandas,polars
Classifier: Development Status :: 4 - Beta
Classifier: License :: OSI Approved :: MIT License
Classifier: Programming Language :: Python
Classifier: Programming Language :: Python :: 3.8
Classifier: Programming Language :: Python :: 3.9
Classifier: Programming Language :: Python :: 3.10
Classifier: Programming Language :: Python :: 3.11
Classifier: Programming Language :: Python :: 3.12
Classifier: Programming Language :: Python :: Implementation :: CPython
Classifier: Programming Language :: Python :: Implementation :: PyPy
Requires-Python: >=3.8
Requires-Dist: haystack-ai>=2.0.0
Requires-Dist: narwhals>=1.1.0
Requires-Dist: typing-extensions
Provides-Extra: pandas
Requires-Dist: pandas>=1.0.0; extra == 'pandas'
Provides-Extra: polars
Requires-Dist: polars>=0.18.0; extra == 'polars'
